{
  "success": true,
  "metadata": {
    "board": "freeboard",
    "page": 1,
    "totalPosts": 30,
    "analyzedAt": "2026-03-15T09:20:36.405Z",
    "processingTime": "293ms"
  },
  "analysis": {
    "timeline": {
      "hourlyDistribution": {
        "17": 4,
        "18": 26
      },
      "peakHours": [
        "18"
      ],
      "peakHourCount": 26,
      "concentration": 86.7
    },
    "keywords": {
      "keywords": [
        {
          "text": "금메달",
          "count": 2,
          "score": 0.5333333333333333
        },
        {
          "text": "요즘",
          "count": 2,
          "score": 0.5333333333333333
        },
        {
          "text": "오늘",
          "count": 2,
          "score": 0.5333333333333333
        },
        {
          "text": "쿠팡",
          "count": 2,
          "score": 0.5333333333333333
        },
        {
          "text": "민주당",
          "count": 2,
          "score": 0.5333333333333333
        }
      ],
      "totalKeywords": 137,
      "uniqueKeywords": 132,
      "avgFrequency": 1.04
    },
    "categories": {
      "categoryDistribution": {
        "정치/검찰": {
          "count": 5,
          "percentage": 16.7
        },
        "국제": {
          "count": 4,
          "percentage": 13.3
        },
        "스포츠": {
          "count": 0,
          "percentage": 0
        },
        "연예/종교": {
          "count": 0,
          "percentage": 0
        },
        "경제/쇼핑": {
          "count": 0,
          "percentage": 0
        },
        "일상": {
          "count": 0,
          "percentage": 0
        },
        "기타": {
          "count": 21,
          "percentage": 70
        }
      },
      "topCategory": "기타",
      "topCategoryCount": 21
    },
    "participation": {
      "recommends": {
        "average": 0.4,
        "max": 3,
        "min": 0,
        "median": 0,
        "stdDev": 0.71
      },
      "dislikes": {
        "average": 0,
        "max": 0,
        "min": 0,
        "median": 0,
        "stdDev": 0
      },
      "views": {
        "average": 409.2,
        "max": 1553,
        "min": 14,
        "median": 361,
        "stdDev": 323.68
      },
      "engagement": {
        "highEngagement": 0,
        "mediumEngagement": 0,
        "lowEngagement": 30
      },
      "activityLevel": "낮음"
    },
    "topPosts": [
      {
        "no": "9873666",
        "title": "동맹국 선제타격 들어감 ㄷㄷㄷ",
        "author": "노바테라",
        "views": 1553,
        "recommends": {
          "up": 0,
          "down": 0
        },
        "createdAt": "17:56:18",
        "url": "https://www.ppomppu.co.kr/zboard/view.php?id=freeboard&page=1&divpage=1844&no=9873666"
      },
      {
        "no": "9873668",
        "title": "[단독] 대기업 중복상장 사실상 전면금지 ㄷ",
        "author": "행우니",
        "views": 978,
        "recommends": {
          "up": 2,
          "down": 0
        },
        "createdAt": "18:00:28",
        "url": "https://www.ppomppu.co.kr/zboard/view.php?id=freeboard&page=1&divpage=1844&no=9873668"
      },
      {
        "no": "9873676",
        "title": "뉴이재명 오늘 모임했네요.jpg",
        "author": "크로소버",
        "views": 842,
        "recommends": {
          "up": 1,
          "down": 0
        },
        "createdAt": "18:06:46",
        "url": "https://www.ppomppu.co.kr/zboard/view.php?id=freeboard&page=1&divpage=1844&no=9873676"
      },
      {
        "no": "9873664",
        "title": "마트에 중국빵 조심하세요 방부제 6개월짜리",
        "author": "enerh344",
        "views": 695,
        "recommends": {
          "up": 0,
          "down": 0
        },
        "createdAt": "17:55:09",
        "url": "https://www.ppomppu.co.kr/zboard/view.php?id=freeboard&page=1&divpage=1844&no=9873664"
      },
      {
        "no": "9873677",
        "title": "연봉을 많이 주니까 우물 안 개구리가 된다",
        "author": "이재명은합니다",
        "views": 691,
        "recommends": {
          "up": 1,
          "down": 0
        },
        "createdAt": "18:08:24",
        "url": "https://www.ppomppu.co.kr/zboard/view.php?id=freeboard&page=1&divpage=1844&no=9873677"
      }
    ],
    "metadata": {
      "totalPosts": 30,
      "analyzedAt": "2026-03-15T09:20:36.405Z",
      "processingTime": "0ms"
    }
  }
}